[
    {
        "name": "swap gen yor 2xn",
        "ref_ener": -1.8573730129353958,
        "energy": -1.8573722799824068,
        "energy_array": [
            -1.837069594503411,
            -0.8743338691534508,
            -1.8568822631026758,
            -1.85737223402713,
            -1.8573722799824068
        ],
        "param": [
            -3.565479802090659e-08,
            0.11174817693361193,
            -3.646750374581289e-08
        ],
        "addition_res:": [
            1.9999999995379607,
            4.000000340693059,
            3.425412158364338e-07,
            0.9999984315529814
        ],
        "optimizer": "L_BFGS_B",
        "gate_count": {
            "rz": 44,
            "rx": 43,
            "delay": 23,
            "cz": 21
        },
        "dist": 1.23,
        "prob": 5e-06,
        "noise": "ion"
    },
    {
        "name": "swap gen yor 2xn",
        "ref_ener": -1.8573730129353958,
        "energy": -1.8573715480993573,
        "energy_array": [
            -1.8370688870135838,
            -0.8743339625932233,
            -1.8568815318823508,
            -1.8573715021489645,
            -1.8573715480993573
        ],
        "param": [
            -3.158784656681468e-08,
            0.11174817305582374,
            -3.2261489061263214e-08
        ],
        "addition_res:": [
            2.0000000002274048,
            4.0000006836889686,
            6.827793495034484e-07,
            0.9999968642602319
        ],
        "optimizer": "L_BFGS_B",
        "gate_count": {
            "rz": 44,
            "rx": 43,
            "delay": 23,
            "cz": 21
        },
        "dist": 1.23,
        "prob": 1e-05,
        "noise": "ion"
    },
    {
        "name": "swap gen yor 2xn",
        "ref_ener": -1.8573730129353958,
        "energy": -1.857299930163532,
        "energy_array": [
            -1.836999659607301,
            -0.8743431928357288,
            -1.8568099692602686,
            -1.8572998842219386,
            -1.857299930163532
        ],
        "param": [
            -3.7055546017496205e-08,
            0.11174634878212925,
            -4.031010647992549e-08
        ],
        "addition_res:": [
            2.000000213582518,
            4.000034602457856,
            3.374812773948577e-05,
            0.9998433482733994
        ],
        "optimizer": "L_BFGS_B",
        "gate_count": {
            "rz": 44,
            "rx": 43,
            "delay": 23,
            "cz": 21
        },
        "dist": 1.23,
        "prob": 0.0005,
        "noise": "ion"
    },
    {
        "name": "swap gen yor 2xn",
        "ref_ener": -1.8573730129353958,
        "energy": -1.857226852782608,
        "energy_array": [
            -1.8369290212693543,
            -0.8743526081468266,
            -1.8567369483485612,
            -1.857226806855032,
            -1.857226852782608
        ],
        "param": [
            -3.1814697916066394e-08,
            0.11174450151740135,
            -3.960478341535256e-08
        ],
        "addition_res:": [
            2.000000427083451,
            4.000069203526499,
            6.749519251325609e-05,
            0.9996867242864949
        ],
        "optimizer": "L_BFGS_B",
        "gate_count": {
            "rz": 44,
            "rx": 43,
            "delay": 23,
            "cz": 21
        },
        "dist": 1.23,
        "prob": 0.001,
        "noise": "ion"
    }
]