[
    {
        "name": "bk_lex",
        "ref_ener": -1.8573730129353958,
        "energy": -1.8573724846395097,
        "energy_array": [
            -1.8370697872538628,
            -1.6233945527227502,
            -1.857348640334386,
            -1.857372482851775,
            -1.8573724846395097
        ],
        "param": [
            0.2234965115028936,
            -3.021257088432799e-08,
            -3.815903507892298e-08
        ],
        "addition_res:": [
            1.9999999820695238,
            4.000000277646504,
            3.4936840842547667e-07,
            0.9999991698388675
        ],
        "optimizer": "L_BFGS_B",
        "gate_count": {
            "rz": 32,
            "rx": 31,
            "cz": 15
        },
        "dist": 1.23,
        "prob": 5e-06,
        "noise": "sc"
    },
    {
        "name": "bk_lex",
        "ref_ener": -1.8573730129353958,
        "energy": -1.857371956343879,
        "energy_array": [
            -1.8370692714565369,
            -1.6233941307933835,
            -1.8573481121594426,
            -1.857371954557137,
            -1.857371956343879
        ],
        "param": [
            0.2234964870263104,
            -2.6694280563422286e-08,
            -2.9729871979411965e-08
        ],
        "addition_res:": [
            1.9999999641390633,
            4.000000555292941,
            6.987366867328149e-07,
            0.999998339678493
        ],
        "optimizer": "L_BFGS_B",
        "gate_count": {
            "rz": 32,
            "rx": 31,
            "cz": 15
        },
        "dist": 1.23,
        "prob": 1e-05,
        "noise": "sc"
    },
    {
        "name": "bk_lex",
        "ref_ener": -1.8573730129353958,
        "energy": -1.8573201845873377,
        "energy_array": [
            -1.8370187244990974,
            -1.6233527827159542,
            -1.857296341570981,
            -1.8573201828008576,
            -1.8573201845873377
        ],
        "param": [
            0.22349511556986132,
            -3.267416412572406e-08,
            -3.262311076559339e-08
        ],
        "addition_res:": [
            1.9999982070173288,
            4.000027764300538,
            3.493622800787577e-05,
            0.9999169876224653
        ],
        "optimizer": "L_BFGS_B",
        "gate_count": {
            "rz": 32,
            "rx": 31,
            "cz": 15
        },
        "dist": 1.23,
        "prob": 0.0005,
        "noise": "sc"
    },
    {
        "name": "bk_lex",
        "ref_ener": -1.8573730129353958,
        "energy": -1.8572673587442252,
        "energy_array": [
            -1.8369671483796088,
            -1.6233105928421685,
            -1.8572435168393897,
            -1.8572673569572222,
            -1.8572673587442252
        ],
        "param": [
            0.22349362245662507,
            -3.271776412857646e-08,
            -2.978386846276669e-08
        ],
        "addition_res:": [
            1.999996414165314,
            4.0000555278930205,
            6.98712189066697e-05,
            0.9998339827913099
        ],
        "optimizer": "L_BFGS_B",
        "gate_count": {
            "rz": 32,
            "rx": 31,
            "cz": 15
        },
        "dist": 1.23,
        "prob": 0.001,
        "noise": "sc"
    }
]