[
    {
        "name": "jw",
        "ref_ener": -1.857373012935392,
        "energy": -1.6561207634804525,
        "param": [
            -1.3380800438137283e-08,
            0.10777867578299385
        ],
        "addition_res:": [
            2.0413223911145146,
            4.30420688265449,
            0.13720977818901048
        ],
        "optimizer": "L_BFGS_B",
        "gate_count": {
            "u": 53,
            "cx": 50
        },
        "dist": 1.23,
        "prob": 0.994,
        "noise": "D"
    },
    {
        "name": "jw",
        "ref_ener": -1.857373012935392,
        "energy": -1.7449445260557837,
        "param": [
            -2.1759261388763086e-08,
            0.10963535511285608
        ],
        "addition_res:": [
            2.023415573853528,
            4.170054107581155,
            0.07584352306815223
        ],
        "optimizer": "L_BFGS_B",
        "gate_count": {
            "u": 53,
            "cx": 50
        },
        "dist": 1.23,
        "prob": 0.9968164215561356,
        "noise": "D"
    },
    {
        "name": "jw",
        "ref_ener": -1.857373012935392,
        "energy": -1.79603938481642,
        "param": [
            -2.74146180742358e-08,
            0.1106253313220622
        ],
        "addition_res:": [
            2.0128651063768936,
            4.092778148092717,
            0.0411522116230536
        ],
        "optimizer": "L_BFGS_B",
        "gate_count": {
            "u": 53,
            "cx": 50
        },
        "dist": 1.23,
        "prob": 0.9983108047152937,
        "noise": "D"
    },
    {
        "name": "jw",
        "ref_ener": -1.857373012935392,
        "energy": -1.8243426021526303,
        "param": [
            -2.941111872704614e-08,
            0.11115191224574926
        ],
        "addition_res:": [
            2.0069536238466976,
            4.0499629087589915,
            0.022100060487599826
        ],
        "optimizer": "L_BFGS_B",
        "gate_count": {
            "u": 53,
            "cx": 50
        },
        "dist": 1.23,
        "prob": 0.9991037190506886,
        "noise": "D"
    },
    {
        "name": "jw",
        "ref_ener": -1.857373012935392,
        "energy": -1.839707911349317,
        "param": [
            -2.777395203892599e-08,
            0.11143170244841542
        ],
        "addition_res:": [
            2.003725953940086,
            4.026719822557698,
            0.011802124064591801
        ],
        "optimizer": "L_BFGS_B",
        "gate_count": {
            "u": 53,
            "cx": 50
        },
        "dist": 1.23,
        "prob": 0.9995244365483543,
        "noise": "D"
    },
    {
        "name": "jw",
        "ref_ener": -1.857373012935392,
        "energy": -1.8479604307808528,
        "param": [
            -2.5570058925853316e-09,
            0.1115802883555677
        ],
        "addition_res:": [
            2.001987298100764,
            4.014236883772044,
            0.006283742015248173
        ],
        "optimizer": "L_BFGS_B",
        "gate_count": {
            "u": 53,
            "cx": 50
        },
        "dist": 1.23,
        "prob": 0.9997476677411085,
        "noise": "D"
    },
    {
        "name": "jw",
        "ref_ener": -1.857373012935392,
        "energy": -1.8523675484808457,
        "param": [
            6.773957493730512e-09,
            0.11165909040801263
        ],
        "addition_res:": [
            2.0010573702405234,
            4.00757083577424,
            0.0033402367803212485
        ],
        "optimizer": "L_BFGS_B",
        "gate_count": {
            "u": 53,
            "cx": 50
        },
        "dist": 1.23,
        "prob": 0.9998661134099835,
        "noise": "D"
    },
    {
        "name": "jw",
        "ref_ener": -1.857373012935392,
        "energy": -1.8547139758896634,
        "param": [
            -1.6302068473791695e-08,
            0.11170093753185878
        ],
        "addition_res:": [
            2.0005618598022967,
            4.0040217961990185,
            0.0017740413033937585
        ],
        "optimizer": "L_BFGS_B",
        "gate_count": {
            "u": 53,
            "cx": 50
        },
        "dist": 1.23,
        "prob": 0.9999289602563501,
        "noise": "D"
    },
    {
        "name": "jw",
        "ref_ener": -1.857373012935392,
        "energy": -1.85596124791692,
        "param": [
            -2.4739924253036155e-08,
            0.11172313715911719
        ],
        "addition_res:": [
            2.00029835273802,
            4.0021352858777535,
            0.0009417859113174387
        ],
        "optimizer": "L_BFGS_B",
        "gate_count": {
            "u": 53,
            "cx": 50
        },
        "dist": 1.23,
        "prob": 0.9999623065672432,
        "noise": "D"
    },
    {
        "name": "jw",
        "ref_ener": -1.857373012935392,
        "energy": -1.8566236848946578,
        "param": [
            1.0665833288275033e-08,
            0.11173492729549225
        ],
        "addition_res:": [
            2.000158370229403,
            4.0011333511406075,
            0.0004998451418662953
        ],
        "optimizer": "L_BFGS_B",
        "gate_count": {
            "u": 53,
            "cx": 50
        },
        "dist": 1.23,
        "prob": 0.99998,
        "noise": "D"
    }
]